qy_soulmate_drawing_generator/__init__.py
qy_soulmate_drawing_generator-1766.746.225.dist-info/licenses/LICENSE
qy_soulmate_drawing_generator-1766.746.225.dist-info/METADATA
qy_soulmate_drawing_generator-1766.746.225.dist-info/WHEEL
qy_soulmate_drawing_generator-1766.746.225.dist-info/top_level.txt
qy_soulmate_drawing_generator-1766.746.225.dist-info/RECORD
