Metadata-Version: 2.4
Name: qy-soulmate-drawing-generator
Version: 1766.746.225
Summary: Professional AI Soulmate Drawing Generation. Easily integrate high-quality AI artwork into your Python applications with https://supermaker.ai/image/ai-soulmate-drawing-generator
Home-page: https://supermaker.ai/image/ai-soulmate-drawing-generator
Author: SuperMaker
Classifier: Programming Language :: Python :: 3
Classifier: License :: OSI Approved :: MIT License
Requires-Python: >=3.6
License-File: LICENSE
Dynamic: author
Dynamic: classifier
Dynamic: description
Dynamic: description-content-type
Dynamic: home-page
Dynamic: license-file
Dynamic: requires-python
Dynamic: summary
